rebis/__init__.py
rebis/rebis.py
rebis-0.1.0.dist-info/METADATA
rebis-0.1.0.dist-info/WHEEL
rebis-0.1.0.dist-info/top_level.txt
rebis-0.1.0.dist-info/RECORD
